mex_gene_archive/__init__.py
mex_gene_archive/_version.py
mex_gene_archive/anndata.py
mex_gene_archive/filter.py
mex_gene_archive/manifest.py
mex_gene_archive/reader.py
mex_gene_archive/starsolo.py
tests/__init__.py
tests/stage_data.py
tests/test_anndata.py
tests/test_filter.py
tests/test_manifest.py
tests/test_starsolo.py
mex_gene_archive-0.2.3.dist-info/LICENSE.txt
mex_gene_archive-0.2.3.dist-info/METADATA
mex_gene_archive-0.2.3.dist-info/WHEEL
mex_gene_archive-0.2.3.dist-info/top_level.txt
mex_gene_archive-0.2.3.dist-info/RECORD
