Metadata-Version: 2.1
Name: mex-gene-archive
Version: 0.2.3
Summary: matrix market tar archive access utilities
Home-page: https://github.com/detrout/mex_gene_archive
Author: Diane Trout
Author-email: diane@caltech.edu
License: BSD-3
Project-URL: Source, https://github.com/detrout/mex_gene_archive
Project-URL: Tracker, https://github.com/detrout/mex_gene_archive/issues
License-File: LICENSE.txt
Provides-Extra: test
Requires-Dist: pytest ; extra == 'test'
Requires-Dist: numpy ; extra == 'test'
Requires-Dist: anndata ; extra == 'test'
